django_vditor-1.1.3.dist-info/METADATA
django_vditor-1.1.3.dist-info/WHEEL
django_vditor-1.1.3.dist-info/entry_points.txt
django_vditor-1.1.3.dist-info/licenses/LICENSE
vditor_app/__init__.py
vditor_app/admin.py
vditor_app/apps.py
vditor_app/forms.py
vditor_app/migrations/0001_initial.py
vditor_app/migrations/__init__.py
vditor_app/models.py
vditor_app/templates/form.html
vditor_app/tests.py
vditor_app/urls.py
vditor_app/views.py
vditor_demo/__init__.py
vditor_demo/asgi.py
vditor_demo/settings.py
vditor_demo/urls.py
vditor_demo/wsgi.py
django_vditor-1.1.3.dist-info/RECORD
