Metadata-Version: 2.1
Name: django-vditor
Version: 1.1.3
Summary: A WYSIWYG editor plugin made by vditor for django
Keywords: django,editor,django-application
Author-Email: pi-dal <hi@pi-dal.com>
License: MIT
Project-URL: Homepage, https://pypi.org/project/django-vditor
Project-URL: Repository, https://github.com/pi-dal/django-vditor
Project-URL: Documentation, https://github.com/pi-dal/django-vditor/blob/main/README.md
Requires-Python: >=3.10
Requires-Dist: django>=5.2
Requires-Dist: werkzeug
